sfera/__init__.py
sfera-1.0.0.dist-info/LICENSE
sfera-1.0.0.dist-info/METADATA
sfera-1.0.0.dist-info/WHEEL
sfera-1.0.0.dist-info/top_level.txt
sfera-1.0.0.dist-info/RECORD
