Metadata-Version: 2.1
Name: sfera
Version: 1.0.0
Summary: SFERA Institute's Python codebase.
Home-page: https://github.com/sfera-institute/python
Author: SFERA Institute
Author-email: hello@sfera.institute
License: UNKNOWN
Project-URL: Documentation, https://github.com/sfera-institute/python
Project-URL: Source, https://github.com/sfera-institute/python
Project-URL: Tracker, https://github.com/sfera-institute/python/issues
Platform: UNKNOWN
Classifier: Development Status :: 3 - Alpha
Classifier: Intended Audience :: Developers
Classifier: License :: OSI Approved :: MIT License
Classifier: Operating System :: OS Independent
Classifier: Programming Language :: Python :: 3
Requires-Python: >=3.6
Requires-Dist: click
Requires-Dist: mkdocs
